env_pipes/__init__.py
env_pipes/__main__.py
env_pipes-0.1.4.dist-info/LICENSE
env_pipes-0.1.4.dist-info/METADATA
env_pipes-0.1.4.dist-info/WHEEL
env_pipes-0.1.4.dist-info/top_level.txt
env_pipes-0.1.4.dist-info/RECORD
